{
  "idea_hash": "fd3ae2db0d7b7f160b947fec9e60c5f6b5918bf1990cf13d44701929164caf61",
  "dataset_fingerprint": "8d2a4e0023ccb7f1aa834662b130d365a02882bb95e48ca05f12edfd25afc04f",
  "generated_ts": 1779380829,
  "status": "COMPLETE_AUDIT_ONLY",
  "title": "RSI oversold + BTC EMA50 + relative volume",
  "provider": "bybit",
  "market_type": "linear",
  "timeframe": "5m",
  "timezone": "America/New_York",
  "session": "NEW_YORK_OPEN",
  "symbols": [
    "SOLUSDT",
    "ETHUSDT"
  ],
  "overall": {
    "known": 10,
    "wins": 0,
    "losses": 10,
    "winrate_pct": 0.0,
    "net_r_simple": -10.0,
    "signals_total": 10,
    "ambiguous": 0,
    "no_touch": 0,
    "duplicate_rate_pct": 0.0,
    "verdict": "NEEDS_MORE_DATA"
  },
  "symbol_results": [
    {
      "symbol": "SOLUSDT",
      "side": "LONG",
      "known": 6,
      "wins": 0,
      "losses": 6,
      "ambiguous": 0,
      "no_touch": 0,
      "winrate_pct": 0.0,
      "net_r_simple": -6.0,
      "max_drawdown_r": -6.0,
      "profit_factor": 0.0,
      "duplicate_rate_pct": 0.0,
      "verdict": "NEEDS_MORE_DATA"
    },
    {
      "symbol": "ETHUSDT",
      "side": "LONG",
      "known": 4,
      "wins": 0,
      "losses": 4,
      "ambiguous": 0,
      "no_touch": 0,
      "winrate_pct": 0.0,
      "net_r_simple": -4.0,
      "max_drawdown_r": -4.0,
      "profit_factor": 0.0,
      "duplicate_rate_pct": 0.0,
      "verdict": "NEEDS_MORE_DATA"
    }
  ],
  "warnings": [],
  "report_markdown": "# StratProof Lab Idea Audit Report\n\n**Idea:** RSI oversold + BTC EMA50 + relative volume\n**Status:** COMPLETE_AUDIT_ONLY\n**Verdict:** NEEDS_MORE_DATA\n**Generated UTC:** 2026-05-21T16:27:09+00:00\n\n## Configuration\n- Provider: `bybit`\n- Market type: `linear`\n- Symbols: `SOLUSDT, ETHUSDT`\n- Timeframe: `5m`\n- Timezone: `America/New_York`\n- Session: `NEW_YORK_OPEN`\n- Side: `LONG`\n- Score threshold: `70`\n\n## Overall Results\n- Known outcomes: **10**\n- Wins: **0**\n- Losses: **10**\n- Winrate: **0.0%**\n- Net R simple: **-10.0**\n- Duplicate rate: **0.0%**\n\n## Symbol Results\n| Symbol | Side | Known | Wins | Losses | WR % | Net R | Max DD | Verdict |\n|---|---:|---:|---:|---:|---:|---:|---:|---|\n| SOLUSDT | LONG | 6 | 0 | 6 | 0.0 | -6.0 | -6.0 | NEEDS_MORE_DATA |\n| ETHUSDT | LONG | 4 | 0 | 4 | 0.0 | -4.0 | -4.0 | NEEDS_MORE_DATA |\n\n## Warnings\n- None\n\n## Safety\nThis report is audit-only. It validates evidence and does not execute broker actions.\n"
}